{
	"info": {
		"_postman_id": "4eaaf565-c255-48b1-b0c8-a1c07ca8689b",
		"name": "Stratplus",
		"schema": "https://schema.getpostman.com/json/collection/v2.1.0/collection.json",
		"_exporter_id": "2851213"
	},
	"item": [
		{
			"name": "Create User",
			"request": {
				"method": "POST",
				"header": [],
				"body": {
					"mode": "raw",
					"raw": "{\r\n    \"email\": \"adm1in@gmail.com\",\r\n    \"password\": \"H12a3456.\",\r\n    \"user\": \"Hello123\",\r\n    \"phone\": \"1231231333\"\r\n}\r\n",
					"options": {
						"raw": {
							"language": "json"
						}
					}
				},
				"url": {
					"raw": "http://127.0.0.1:8097/api/v1/users",
					"protocol": "http",
					"host": [
						"127",
						"0",
						"0",
						"1"
					],
					"port": "8097",
					"path": [
						"api",
						"v1",
						"users"
					]
				}
			},
			"response": []
		},
		{
			"name": "Auth User",
			"request": {
				"method": "POST",
				"header": [],
				"body": {
					"mode": "raw",
					"raw": "{\r\n    \"email\": \"admin@gmail.com\",\r\n    \"password\": \"H12a3456.\"\r\n}\r\n",
					"options": {
						"raw": {
							"language": "json"
						}
					}
				},
				"url": {
					"raw": "http://127.0.0.1:8097/api/v1/users/auth",
					"protocol": "http",
					"host": [
						"127",
						"0",
						"0",
						"1"
					],
					"port": "8097",
					"path": [
						"api",
						"v1",
						"users",
						"auth"
					]
				}
			},
			"response": []
		}
	]
}